MysqlTick/__init__.py
MysqlTick/Loopback/__init__.py
MysqlTick/Loopback/mysqlTickCache.py
MysqlTick/Loopback/scanZToneDay3.py
MysqlTick/Loopback/scanZToneDay3bak.py
Tools/__init__.py
Tools/osPATH.py
rqalpha/__init__.py
rqalpha/__main__.py
rqalpha/const.py
rqalpha/environment.py
rqalpha/events.py
rqalpha/execution_context.py
rqalpha/interface.py
rqalpha/main.py
rqalpha/preparetTickDataLoopback.py
rqalpha/read_pickle.py
rqalpha/testTick.py
rqalpha/testTick_test.py
rqalpha/testone.py
rqalpha/updae_bundle.py
rqalpha/user_module.py
rqalpha/DBStock/__init__.py
rqalpha/DBStock/dbQueryPools.py
rqalpha/DBStock/mysqlCache.py
rqalpha/DBStock/mysqlResult.py
rqalpha/api/__init__.py
rqalpha/api/api_base.py
rqalpha/api/api_extension.py
rqalpha/api/helper.py
rqalpha/api/names.py
rqalpha/core/__init__.py
rqalpha/core/bar_dict_price_board.py
rqalpha/core/executor.py
rqalpha/core/global_var.py
rqalpha/core/strategy.py
rqalpha/core/strategy_context.py
rqalpha/core/strategy_loader.py
rqalpha/core/strategy_universe.py
rqalpha/data/__init__.py
rqalpha/data/adjust.py
rqalpha/data/base_data_source.py
rqalpha/data/converter.py
rqalpha/data/data_proxy.py
rqalpha/data/date_set.py
rqalpha/data/daybar_store.py
rqalpha/data/dividend_store.py
rqalpha/data/future_info_cn.py
rqalpha/data/instrument_mixin.py
rqalpha/data/instrument_store.py
rqalpha/data/public_fund_commission.py
rqalpha/data/risk_free_helper.py
rqalpha/data/simple_factor_store.py
rqalpha/data/trading_dates_mixin.py
rqalpha/data/trading_dates_store.py
rqalpha/data/yield_curve_store.py
rqalpha/examples/IF_macd.py
rqalpha/examples/__init__.py
rqalpha/examples/buy_and_hold.py
rqalpha/examples/buy_and_hold_Tick.py
rqalpha/examples/buy_and_hold_Tick_test.py
rqalpha/examples/golden_cross.py
rqalpha/examples/macd.py
rqalpha/examples/pair_trading.py
rqalpha/examples/prepare_data_Tick.py
rqalpha/examples/rsi.py
rqalpha/examples/run_code_demo.py
rqalpha/examples/run_file_demo.py
rqalpha/examples/run_func_demo.py
sdufeQuant-1.1.1.dist-info/LICENSE
sdufeQuant-1.1.1.dist-info/METADATA
sdufeQuant-1.1.1.dist-info/WHEEL
sdufeQuant-1.1.1.dist-info/top_level.txt
sdufeQuant-1.1.1.dist-info/RECORD
